p/__init__.py
p/cli.py
p/commands.py
p/git.py
p/groups.py
p/run.py
p/types/__init__.py
p/types/base.py
p/types/js.py
p/types/make.py
p/types/scripts.py
p-1.2.5.dist-info/entry_points.txt
p-1.2.5.dist-info/LICENSE
p-1.2.5.dist-info/WHEEL
p-1.2.5.dist-info/METADATA
p-1.2.5.dist-info/RECORD
