Metadata-Version: 2.1
Name: p
Version: 1.2.5
Summary: Aliases any available project commands or scripts to `p <name>`.
Home-page: https://www.dropseed.dev/p
License: MIT
Keywords: cli,alias,commands,scripts,bin
Author: Dave Gaeddert
Author-email: dave.gaeddert@dropseed.dev
Requires-Python: >=3.6.2,<4.0.0
Classifier: License :: OSI Approved :: MIT License
Classifier: Programming Language :: Python :: 3
Classifier: Programming Language :: Python :: 3.10
Classifier: Programming Language :: Python :: 3.7
Classifier: Programming Language :: Python :: 3.8
Classifier: Programming Language :: Python :: 3.9
Requires-Dist: click (>=7.1.2,<8.0.0)
Requires-Dist: cls-client (>=1.2.0,<2.0.0)
Project-URL: Documentation, https://www.dropseed.dev/p
Project-URL: Repository, https://github.com/dropseed/p
